django_scopes/__init__.py
django_scopes/exceptions.py
django_scopes/forms.py
django_scopes/manager.py
django_scopes/state.py
tests/testapp/__init__.py
tests/testapp/apps.py
tests/testapp/forms.py
tests/testapp/models.py
tests/testapp/urls.py
tests/testapp/wsgi.py
tests/testapp/migrations/0001_initial.py
tests/testapp/migrations/0002_bookmark.py
tests/testapp/migrations/0003_commentgroup.py
tests/testapp/migrations/__init__.py
django_scopes-2.0.0.dist-info/AUTHORS
django_scopes-2.0.0.dist-info/LICENSE
django_scopes-2.0.0.dist-info/METADATA
django_scopes-2.0.0.dist-info/WHEEL
django_scopes-2.0.0.dist-info/top_level.txt
django_scopes-2.0.0.dist-info/RECORD
